{
  "collected_at": "2026-01-16T01:06:34.543212",
  "source": "GitHub API",
  "data": [
    {
      "name": "codecrafters-io/build-your-own-x",
      "stars": 456999,
      "language": "Markdown",
      "description": "Master programming by recreating your favorite technologies from scratch.",
      "url": "https://github.com/codecrafters-io/build-your-own-x",
      "updated_at": "2026-01-16T01:05:07Z"
    },
    {
      "name": "freeCodeCamp/freeCodeCamp",
      "stars": 435899,
      "language": "TypeScript",
      "description": "freeCodeCamp.org's open-source codebase and curriculum. Learn math, programming, and computer scienc",
      "url": "https://github.com/freeCodeCamp/freeCodeCamp",
      "updated_at": "2026-01-16T00:52:59Z"
    },
    {
      "name": "sindresorhus/awesome",
      "stars": 429753,
      "language": "N/A",
      "description": "\ud83d\ude0e Awesome lists about all kinds of interesting topics",
      "url": "https://github.com/sindresorhus/awesome",
      "updated_at": "2026-01-16T00:57:29Z"
    },
    {
      "name": "public-apis/public-apis",
      "stars": 391235,
      "language": "Python",
      "description": "A collective list of free APIs",
      "url": "https://github.com/public-apis/public-apis",
      "updated_at": "2026-01-16T01:00:48Z"
    },
    {
      "name": "EbookFoundation/free-programming-books",
      "stars": 380542,
      "language": "Python",
      "description": ":books: Freely available programming books",
      "url": "https://github.com/EbookFoundation/free-programming-books",
      "updated_at": "2026-01-16T00:55:24Z"
    },
    {
      "name": "kamranahmedse/developer-roadmap",
      "stars": 347294,
      "language": "TypeScript",
      "description": "Interactive roadmaps, guides and other educational content to help developers grow in their careers.",
      "url": "https://github.com/kamranahmedse/developer-roadmap",
      "updated_at": "2026-01-16T00:30:42Z"
    },
    {
      "name": "jwasham/coding-interview-university",
      "stars": 335862,
      "language": "N/A",
      "description": "A complete computer science study plan to become a software engineer.",
      "url": "https://github.com/jwasham/coding-interview-university",
      "updated_at": "2026-01-16T01:00:53Z"
    },
    {
      "name": "donnemartin/system-design-primer",
      "stars": 332325,
      "language": "Python",
      "description": "Learn how to design large-scale systems. Prep for the system design interview.  Includes Anki flashc",
      "url": "https://github.com/donnemartin/system-design-primer",
      "updated_at": "2026-01-16T00:05:19Z"
    },
    {
      "name": "vinta/awesome-python",
      "stars": 278374,
      "language": "Python",
      "description": "An opinionated list of awesome Python frameworks, libraries, software and resources.",
      "url": "https://github.com/vinta/awesome-python",
      "updated_at": "2026-01-16T00:58:34Z"
    },
    {
      "name": "996icu/996.ICU",
      "stars": 275167,
      "language": "N/A",
      "description": "Repo for counting stars and contributing. Press F to pay respect to glorious developers.",
      "url": "https://github.com/996icu/996.ICU",
      "updated_at": "2026-01-16T00:32:27Z"
    }
  ]
}